python_soql_parser/__init__.py
python_soql_parser/binops.py
python_soql_parser/core.py
python_soql_parser/tokens.py
python_soql_parser-0.2.0.dist-info/WHEEL
python_soql_parser-0.2.0.dist-info/METADATA
python_soql_parser-0.2.0.dist-info/RECORD
