Metadata-Version: 2.1
Name: python-soql-parser
Version: 0.2.0
Summary: A pyparsing-based library for parsing SOQL statements
Home-page: https://github.com/Kicksaw-Consulting/python-soql-parser
License: MIT
Keywords: python,soql,pyparsing,parsing,salesforce
Author: Alex Drozd
Author-email: drozdster@gmail.com
Requires-Python: >=3.8,<4.0
Classifier: License :: OSI Approved :: MIT License
Classifier: Programming Language :: Python :: 3
Classifier: Programming Language :: Python :: 3.8
Classifier: Programming Language :: Python :: 3.9
Classifier: Programming Language :: Python :: 3.10
Requires-Dist: pyparsing (>=2.4.7,<3.0.0)
Project-URL: Repository, https://github.com/Kicksaw-Consulting/python-soql-parser
